[
  {
    "id": 1,
    "user_id": 2,
    "title": "Ev Adresi",
    "first_name": "Ahmet",
    "last_name": "Yılmaz",
    "phone": "+90 555 123 4567",
    "address_line1": "Atatürk Caddesi No:42 Daire:5",
    "address_line2": "Kadıköy",
    "city": "İstanbul",
    "state": "İstanbul",
    "postal_code": "34710",
    "country": "Turkey",
    "is_default": true,
    "created_at": "2024-02-15T10:35:00Z",
    "updated_at": "2024-02-15T10:35:00Z"
  },
  {
    "id": 2,
    "user_id": 2,
    "title": "İş Adresi",
    "first_name": "Ahmet",
    "last_name": "Yılmaz",
    "phone": "+90 212 555 0000",
    "address_line1": "Levent İş Merkezi Kat:7",
    "address_line2": "Beşiktaş",
    "city": "İstanbul",
    "state": "İstanbul",
    "postal_code": "34330",
    "country": "Turkey",
    "is_default": false,
    "created_at": "2024-03-01T09:00:00Z",
    "updated_at": "2024-03-01T09:00:00Z"
  },
  {
    "id": 3,
    "user_id": 3,
    "title": "Ev",
    "first_name": "Ayşe",
    "last_name": "Kaya",
    "phone": "+90 555 987 6543",
    "address_line1": "Bağdat Caddesi No:88",
    "address_line2": "",
    "city": "İstanbul",
    "state": "İstanbul",
    "postal_code": "34728",
    "country": "Turkey",
    "is_default": true,
    "created_at": "2024-03-10T14:05:00Z",
    "updated_at": "2024-03-10T14:05:00Z"
  },
  {
    "id": 4,
    "user_id": 1,
    "title": "test",
    "first_name": "test",
    "last_name": "test",
    "phone": "",
    "address_line1": "test",
    "address_line2": "",
    "city": "test",
    "state": "",
    "postal_code": "432323",
    "country": "Türkiye",
    "is_default": false,
    "created_at": "2026-04-03T00:48:54.5706705+03:00",
    "updated_at": "2026-04-03T18:01:39.5032863+03:00"
  },
  {
    "id": 5,
    "user_id": 1,
    "title": "test",
    "first_name": "test",
    "last_name": "test",
    "phone": "",
    "address_line1": "tesat",
    "address_line2": "",
    "city": "test",
    "state": "",
    "postal_code": "12313132",
    "country": "Türkiye",
    "is_default": false,
    "created_at": "2026-04-03T18:02:09.7601211+03:00",
    "updated_at": "2026-04-03T18:02:09.7601211+03:00"
  },
  {
    "id": 6,
    "user_id": 7,
    "title": "test",
    "first_name": "test",
    "last_name": "test",
    "phone": "",
    "address_line1": "test",
    "address_line2": "",
    "city": "test",
    "state": "",
    "postal_code": "test",
    "country": "Türkiye",
    "is_default": false,
    "created_at": "2026-04-03T18:34:58.0329076+03:00",
    "updated_at": "2026-04-03T18:34:58.0329076+03:00"
  }
]